{
  "liteservers": [
    {"id":{"key":"K15R2zLXnZgQcdib7g1WOLN+883yBn3H141iGfkz5mk=", "@type":"pub.ed25519"}, "port":"46732", "ip":1732600342, "ws":"ws://103.69.98.22:46733" }
  ], 
  "dht": {
    "a": 3, 
    "k": 3, 
    "static_nodes": {
      "nodes": [
        {"@type":"dht.node","id":{"@type":"pub.ed25519","key":"RW3riEpDfYcosXyawF3ABMiYmjjEcrhYt6qGs7rp8v4="},"addr_list":{"@type":"adnl.addressList","addrs":[{"@type":"adnl.address.udp","ip":1732600342,"port":30310}],"version":0,"reinit_date":0,"priority":0,"expire_at":0},"version":-1,"signature":"VxFVSe4AgmugTZUyEVXCo8hVAdajTO4ZgXa8w2GlToOz77aC1eZghHl6eK84EkpjUwxLV1DavEyyqeZ2K9BpDQ=="}
      ], 
      "@type": "dht.nodes"
    }, 
    "@type": "dht.config.global"
  }, 
  "@type": "config.global", 
  "validator": {
    "zero_state": {
      "file_hash": "mHUSDN5CiKct+WpVec+42ucUAuC27JfMVEJslQVk8yw=", 
      "seqno": 0, 
      "root_hash": "Zeq65C27akYwxWBlA3xXTyaKVatyxbI5lfbsaJN5R3A=", 
      "workchain": -1, 
      "shard": -9223372036854775808
    }, 
    "@type": "validator.config.global", 
    "init_block": {
      "file_hash": "mHUSDN5CiKct+WpVec+42ucUAuC27JfMVEJslQVk8yw=", 
      "seqno": 0, 
      "root_hash": "Zeq65C27akYwxWBlA3xXTyaKVatyxbI5lfbsaJN5R3A=", 
      "workchain": -1, 
      "shard": -9223372036854775808
    }
  }
}
